jupyterpack/__init__.py
jupyterpack/_version.py
jupyterpack/asgi/__init__.py
jupyterpack/asgi/asgiBridge.py
jupyterpack/asgi/asgiServer.py
jupyterpack/asgi/websocketHandler.py
jupyterpack/common/__init__.py
jupyterpack/common/baseBridge.py
jupyterpack/common/baseServer.py
jupyterpack/common/patch.py
jupyterpack/common/tools.py
jupyterpack/dash/__init__.py
jupyterpack/dash/dashServer.py
jupyterpack/dash/tools.py
jupyterpack/js/__init__.py
jupyterpack/js/broadcastChannel.py
jupyterpack/js/comm.py
jupyterpack/js/jsLog.py
jupyterpack/panel/__init__.py
jupyterpack/panel/panelServer.py
jupyterpack/panel/tools.py
jupyterpack/shiny/__init__.py
jupyterpack/shiny/shinyServer.py
jupyterpack/shiny/tools.py
jupyterpack/starlette/__init__.py
jupyterpack/starlette/starletteServer.py
jupyterpack/streamlit/__init__.py
jupyterpack/streamlit/streamlitServer.py
jupyterpack/streamlit/tools.py
jupyterpack/textual/__init__.py
jupyterpack/textual/textualBridge.py
jupyterpack/textual/textualDriver.py
jupyterpack/textual/textualServer.py
jupyterpack/textual/tools.py
jupyterpack/tornado/__init__.py
jupyterpack/tornado/connectionState.py
jupyterpack/tornado/patchedConnection.py
jupyterpack/tornado/tools.py
jupyterpack/tornado/tornadoBridge.py
jupyterpack/tornado/tornadoServer.py
jupyterpack/tornado/wsConnection.py
jupyterpack/wsgi/__init__.py
jupyterpack/wsgi/wsgiBridge.py
jupyterpack/wsgi/wsgiServer.py
jupyterpack-0.5.6.data/data/share/jupyter/labextensions/jupyterpack/package.json
jupyterpack-0.5.6.data/data/share/jupyter/labextensions/jupyterpack/static/17.b058b1e5ebd2000a8c6e.js
jupyterpack-0.5.6.data/data/share/jupyter/labextensions/jupyterpack/static/17.b058b1e5ebd2000a8c6e.js.LICENSE.txt
jupyterpack-0.5.6.data/data/share/jupyter/labextensions/jupyterpack/static/25.fa86dc0826386b41d2c7.js
jupyterpack-0.5.6.data/data/share/jupyter/labextensions/jupyterpack/static/353.6964d519aad188038e8a.js
jupyterpack-0.5.6.dist-info/METADATA
jupyterpack-0.5.6.dist-info/WHEEL
jupyterpack-0.5.6.dist-info/licenses/LICENSE
jupyterpack-0.5.6.dist-info/RECORD
