Metadata-Version: 2.4
Name: jupyterpack
Version: 0.5.6
Summary: A JupyterLab extension for serving web app.
Project-URL: Homepage, https://github.com/trungleduc/jupyterpack
Project-URL: Bug Tracker, https://github.com/trungleduc/jupyterpack/issues
Project-URL: Repository, https://github.com/trungleduc/jupyterpack.git
Author-email: Trung Le <leductrungxf@gmail.com>
License: BSD 3-Clause License
License-File: LICENSE
Keywords: jupyter,jupyterlab,jupyterlab-extension
Classifier: Framework :: Jupyter
Classifier: Framework :: Jupyter :: JupyterLab
Classifier: Framework :: Jupyter :: JupyterLab :: 4
Classifier: Framework :: Jupyter :: JupyterLab :: Extensions
Classifier: Framework :: Jupyter :: JupyterLab :: Extensions :: Prebuilt
Classifier: License :: OSI Approved :: BSD License
Classifier: Programming Language :: Python
Classifier: Programming Language :: Python :: 3
Classifier: Programming Language :: Python :: 3.9
Classifier: Programming Language :: Python :: 3.10
Classifier: Programming Language :: Python :: 3.11
Classifier: Programming Language :: Python :: 3.12
Classifier: Programming Language :: Python :: 3.13
Requires-Python: >=3.10
Requires-Dist: httpx
Requires-Dist: numpy
Requires-Dist: pandas
Requires-Dist: specta>=0.4.6
Requires-Dist: starlette
Requires-Dist: tornado
